{
  "project_info": {
    "project_number": "160046351223",
    "project_id": "shopapp-1f3c7",
    "storage_bucket": "shopapp-1f3c7.firebasestorage.app"
  },
  "client": [
    {
      "client_info": {
        "mobilesdk_app_id": "1:160046351223:android:2ea5d0f38481523b52d772",
        "android_client_info": {
          "package_name": "com.shoesapp"
        }
      },
      "oauth_client": [
        {
          "client_id": "160046351223-26hntuv7hf521s7moanto2ogctknnn53.apps.googleusercontent.com",
          "client_type": 3
        }
      ],
      "api_key": [
        {
          "current_key": "AIzaSyBUBAk8M4hErmRu542fF49JW0tF9uXULV8"
        }
      ],
      "services": {
        "appinvite_service": {
          "other_platform_oauth_client": [
            {
              "client_id": "160046351223-26hntuv7hf521s7moanto2ogctknnn53.apps.googleusercontent.com",
              "client_type": 3
            }
          ]
        }
      }
    }
  ],
  "configuration_version": "1"
}